{
  "version": "1.0",
  "workerIdList": [
    -1,
    2,
    0
  ],
  "metrics": [
    {
      "type": "build_line",
      "endTime": 1708325689935,
      "status": "closed",
      "children": [],
      "name": "overallTime",
      "taskName": "init",
      "taskPath": "entry",
      "workerId": -1,
      "startTime": 1708325689933
    },
    {
      "type": "build_line",
      "endTime": 1708325689942,
      "status": "closed",
      "children": [],
      "name": "overallTime",
      "taskName": "init",
      "taskPath": "CXHeimaHealthy",
      "workerId": -1,
      "startTime": 1708325689942
    },
    {
      "type": "build_line",
      "endTime": 1708325695882,
      "status": "closed",
      "children": [],
      "name": "overallTime",
      "taskName": "default@PreBuild",
      "taskPath": "entry",
      "workerId": -1,
      "startTime": 1708325695835
    },
    {
      "type": "build_line",
      "endTime": 1708325695885,
      "status": "closed",
      "children": [],
      "name": "overallTime",
      "taskName": "default@GenerateMetadata",
      "taskPath": "entry",
      "workerId": -1,
      "startTime": 1708325695883
    },
    {
      "type": "build_line",
      "endTime": 1708325695889,
      "status": "closed",
      "children": [],
      "name": "overallTime",
      "taskName": "default@MergeProfile",
      "taskPath": "entry",
      "workerId": -1,
      "startTime": 1708325695888
    },
    {
      "type": "build_line",
      "endTime": 1708325695890,
      "status": "closed",
      "children": [],
      "name": "overallTime",
      "taskName": "default@BuildNativeWithCmake",
      "taskPath": "entry",
      "workerId": -1,
      "startTime": 1708325695890
    },
    {
      "type": "build_line",
      "endTime": 1708325695894,
      "status": "closed",
      "children": [],
      "name": "overallTime",
      "taskName": "default@GenerateLoaderJson",
      "taskPath": "entry",
      "workerId": -1,
      "startTime": 1708325695893
    },
    {
      "type": "build_line",
      "endTime": 1708325695897,
      "status": "closed",
      "children": [],
      "name": "overallTime",
      "taskName": "default@MakePackInfo",
      "taskPath": "entry",
      "workerId": -1,
      "startTime": 1708325695895
    },
    {
      "type": "build_line",
      "endTime": 1708325695943,
      "status": "closed",
      "children": [],
      "name": "overallTime",
      "taskName": "default@ProcessProfile",
      "taskPath": "entry",
      "workerId": -1,
      "startTime": 1708325695898
    },
    {
      "type": "build_line",
      "endTime": 1708325695944,
      "status": "closed",
      "children": [],
      "name": "overallTime",
      "taskName": "default@BuildNativeWithNinja",
      "taskPath": "entry",
      "workerId": -1,
      "startTime": 1708325695943
    },
    {
      "type": "build_line",
      "endTime": 1708325695946,
      "status": "closed",
      "children": [],
      "name": "overallTime",
      "taskName": "default@ProcessResource",
      "taskPath": "entry",
      "workerId": -1,
      "startTime": 1708325695945
    },
    {
      "type": "build_line",
      "endTime": 1708325695948,
      "status": "closed",
      "children": [],
      "name": "overallTime",
      "taskName": "default@ProcessLibs",
      "taskPath": "entry",
      "workerId": -1,
      "startTime": 1708325695947
    },
    {
      "type": "build_line",
      "endTime": 1708325696055,
      "status": "closed",
      "children": [],
      "name": "overallTime",
      "taskName": "default@CompileResource",
      "taskPath": "entry",
      "workerId": -1,
      "startTime": 1708325695948
    },
    {
      "type": "build_line",
      "endTime": 1708325696060,
      "status": "closed",
      "children": [],
      "name": "overallTime",
      "taskName": "default@CompileJS",
      "taskPath": "entry",
      "workerId": -1,
      "startTime": 1708325696060
    },
    {
      "type": "build_line",
      "endTime": 1708325698647,
      "status": "closed",
      "children": [],
      "name": "overallTime",
      "taskName": "default@CompileArkTS",
      "taskPath": "entry",
      "workerId": 2,
      "startTime": 1708325696059
    },
    {
      "type": "default",
      "endTime": 1708325698647,
      "status": "closed",
      "children": [
        {
          "type": "build_line",
          "endTime": 1708325698647,
          "status": "closed",
          "children": [],
          "name": "overallTime",
          "taskName": "default@CompileArkTS",
          "taskPath": "entry",
          "workerId": 2,
          "startTime": 1708325696059
        }
      ],
      "name": "overallTime",
      "taskName": "default@CompileArkTS",
      "taskPath": "entry",
      "workerId": -1,
      "startTime": 1708325696056
    },
    {
      "type": "build_line",
      "endTime": 1708325699173,
      "status": "closed",
      "children": [],
      "name": "overallTime",
      "taskName": "default@PackageHap",
      "taskPath": "entry",
      "workerId": 0,
      "startTime": 1708325698650
    },
    {
      "type": "default",
      "endTime": 1708325699173,
      "status": "closed",
      "children": [
        {
          "type": "build_line",
          "endTime": 1708325699173,
          "status": "closed",
          "children": [],
          "name": "overallTime",
          "taskName": "default@PackageHap",
          "taskPath": "entry",
          "workerId": 0,
          "startTime": 1708325698650
        }
      ],
      "name": "overallTime",
      "taskName": "default@PackageHap",
      "taskPath": "entry",
      "workerId": -1,
      "startTime": 1708325698648
    },
    {
      "type": "build_line",
      "endTime": 1708325699174,
      "status": "closed",
      "children": [],
      "name": "overallTime",
      "taskName": "default@SignHap",
      "taskPath": "entry",
      "workerId": -1,
      "startTime": 1708325699173
    },
    {
      "type": "build_line",
      "endTime": 1708325699174,
      "status": "closed",
      "children": [],
      "name": "overallTime",
      "taskName": "assembleHap",
      "taskPath": "entry",
      "workerId": -1,
      "startTime": 1708325699174
    }
  ],
  "workLog": []
}